Metadata-Version: 2.1
Name: oneNeuron-pypi-AnkitJha16
Version: 0.0.1
Summary: Its an Implementation of perceptron
Home-page: https://github.com/AnkitJha16/oneNeuron_pypi
Author: AnkitJha16
Author-email: freelancer.ankit.jha@gmail.com
License: UNKNOWN
Project-URL: Bug Tracker, https://github.com/AnkitJha16/oneNeuron_pypi/issues
Platform: UNKNOWN
Classifier: Programming Language :: Python :: 3
Classifier: License :: OSI Approved :: MIT License
Classifier: Operating System :: OS Independent
Requires-Python: >=3.7
License-File: LICENSE
Requires-Dist: numpy
Requires-Dist: logging
Requires-Dist: tqdm
